{
  "name": "dungeons:dungeon_arena_ceiling",
  "fallback": "minecraft:empty",
  "elements": [
    {
      "weight": 40,
      "element": {
        "location": "dungeons:dungeon_arena_platform",
        "processors": "minecraft:empty",
		    "projection": "rigid",
        "element_type": "minecraft:single_pool_element"
      }
    },
    {
      "weight": 60,
      "element": {
        "location": "dungeons:dungeon_arena_platform",
        "processors": "minecraft:empty",
		    "projection": "rigid",
        "element_type": "minecraft:empty_pool_element"
      }
    }
  ]
}